{
  "title": "Section Registrations Grade Options",
  "description": "The grading options for the section registration.",
  "type": "object",
  "properties": {
    "metadata": {
      "title": "Metadata",
      "description": "Metadata about the JSON payload",
      "type": "object",
      "properties": {
        "createdBy": {
          "title": "Created By",
          "description": "The name of the originator (user or system) of the data. This is informational only, do not use in business logic!",
          "type": "string"
        },
        "createdOn": {
          "title": "Created On",
          "description": "The date and time when the entity instance was created",
          "oneOf": [
            {
              "type": "string",
              "format": "date-time",
              "pattern": "^(-?(?:[1-9][0-9]*)?[0-9]{4})-(1[0-2]|0[1-9])-(3[0-1]|0[1-9]|[1-2][0-9])T(2[0-3]|[0-1][0-9]):([0-5][0-9]):([0-5][0-9])(\\.[0-9]+)?(Z|[+-](?:2[0-3]|[0-1][0-9]):[0-5][0-9])?$"
            },
            {
              "type": "string",
              "maxLength": 0
            }
          ]
        },
        "modifiedBy": {
          "title": "Modified By",
          "description": "The name of the modifier (user or system) of the data. This is informational only, do not use in business logic!",
          "type": "string"
        },
        "modifiedOn": {
          "title": "Modified On",
          "description": "The date and time when the entity instance was last modified",
          "oneOf": [
            {
              "type": "string",
              "format": "date-time",
              "pattern": "^(-?(?:[1-9][0-9]*)?[0-9]{4})-(1[0-2]|0[1-9])-(3[0-1]|0[1-9]|[1-2][0-9])T(2[0-3]|[0-1][0-9]):([0-5][0-9]):([0-5][0-9])(\\.[0-9]+)?(Z|[+-](?:2[0-3]|[0-1][0-9]):[0-5][0-9])?$"
            },
            {
              "type": "string",
              "maxLength": 0
            }
          ]
        }
      },
      "additionalProperties": false
    },
    "id": {
      "title": "ID",
      "description": "The global identifier of the section registration.",
      "type": "string",
      "format": "guid",
      "pattern": "^[a-f0-9]{8}(?:-[a-f0-9]{4}){3}-[a-f0-9]{12}$"
    },
    "section": {
      "title": "Section",
      "description": "An instance of a course for which a person has registered.",
      "type": "object",
      "properties": {
        "id": {
          "title": "ID",
          "description": "The global identifier for the Section.",
          "type": "string",
          "format": "guid",
          "pattern": "^[a-f0-9]{8}(?:-[a-f0-9]{4}){3}-[a-f0-9]{12}$"
        }
      },
      "additionalProperties": false,
      "required": [
        "id"
      ]
    },
    "sectionGradability": {
      "title": "Section Gradability",
      "description": "An indicator whether the section is gradable.",
      "oneOf": [
        {
          "type": "string",
          "enum": [
            "notGradable",
            "gradable"
          ]
        },
        {
          "type": "string",
          "maxLength": 0
        }
      ]
    },
    "studentGradeScheme": {
      "title": "Student Grade Scheme",
      "description": "The grading scheme used to award the student their grade for the section.",
      "oneOf": [
        {
          "type": "object",
          "properties": {
            "detail": {
              "title": "Detail",
              "description": "The grading scheme used to award the student their grade for the section.",
              "type": "object",
              "properties": {
                "id": {
                  "title": "ID",
                  "description": "The global identifier for the Detail.",
                  "type": "string",
                  "format": "guid",
                  "pattern": "^[a-f0-9]{8}(?:-[a-f0-9]{4}){3}-[a-f0-9]{12}$"
                }
              },
              "additionalProperties": false,
              "required": [
                "id"
              ]
            },
            "title": {
              "title": "Title",
              "description": "The full name of the grading scheme.",
              "type": "string"
            }
          },
          "additionalProperties": false,
          "required": [
            "detail"
          ]
        },
        {
          "type": "object",
          "maxProperties": 0
        }
      ]
    },
    "gradeStatus": {
      "title": "Grade Status",
      "description": "An indicator whether the student has a verified grade or the section registration.",
      "oneOf": [
        {
          "type": "string",
          "enum": [
            "verified",
            "unverified"
          ]
        },
        {
          "type": "string",
          "maxLength": 0
        }
      ]
    },
    "grades": {
      "title": "Grades",
      "description": "The grade options associated with the section registration.",
      "type": "array",
      "items": {
        "type": "object",
        "properties": {
          "grade": {
            "title": "Grade",
            "description": "The grade that may be awarded to the student by the instructor.",
            "type": "object",
            "properties": {
              "id": {
                "title": "ID",
                "description": "The global identifier for the Grade.",
                "type": "string",
                "format": "guid",
                "pattern": "^[a-f0-9]{8}(?:-[a-f0-9]{4}){3}-[a-f0-9]{12}$"
              }
            },
            "additionalProperties": false,
            "required": [
              "id"
            ]
          },
          "value": {
            "title": "Value",
            "description": "The grade value.",
            "type": "string"
          },
          "incompleteGradeDetails": {
            "title": "Incomplete Grade Details",
            "description": "The incomplete grade details associated with the grade.",
            "type": "object",
            "properties": {
              "finalGradeDefault": {
                "title": "Final Grade Default",
                "description": "The default final grade to be assigned to this section registration when extension date is passed.",
                "oneOf": [
                  {
                    "type": "object",
                    "properties": {
                      "id": {
                        "title": "ID",
                        "description": "The global identifier for the Final Grade Default.",
                        "type": "string",
                        "format": "guid",
                        "pattern": "^[a-f0-9]{8}(?:-[a-f0-9]{4}){3}-[a-f0-9]{12}$"
                      }
                    },
                    "additionalProperties": false,
                    "required": [
                      "id"
                    ]
                  },
                  {
                    "type": "object",
                    "maxProperties": 0
                  }
                ]
              },
              "finalGradeDefaultOverridability": {
                "title": "Final Grade Default Overridability",
                "description": "An indicator whether the instructor may override the default final grade.",
                "oneOf": [
                  {
                    "type": "string",
                    "enum": [
                      "overridable",
                      "notOverridable"
                    ]
                  },
                  {
                    "type": "string",
                    "maxLength": 0
                  }
                ]
              },
              "extensionDateDefault": {
                "title": "Extension Date Default",
                "description": "The default extension date associated with the incomplete grade.",
                "oneOf": [
                  {
                    "type": "string",
                    "format": "date",
                    "pattern": "^(-?(?:[1-9][0-9]*)?[0-9]{4})-(1[0-2]|0[1-9])-(3[0-1]|0[1-9]|[1-2][0-9])$"
                  },
                  {
                    "type": "string",
                    "maxLength": 0
                  }
                ]
              }
            },
            "additionalProperties": false
          },
          "lastDateOfAttendanceRequiredness": {
            "title": "Last Date Of Attendance Requiredness",
            "description": "An indicator whether the last date of attendance is required for the grade.",
            "oneOf": [
              {
                "type": "string",
                "enum": [
                  "required",
                  "notRequired"
                ]
              },
              {
                "type": "string",
                "maxLength": 0
              }
            ]
          }
        },
        "additionalProperties": false,
        "required": [
          "grade"
        ]
      }
    }
  },
  "required": [
    "id",
    "section"
  ],
  "additionalProperties": false
}